src/UnidadDeControl/bttnTest.v
module bttnTest #(parameter COUNT_MAX = 25000000,FiveSegs = 10)(
    // Declaración de entradas y salidas
    input botonTest,
    input clk,
    input rst,
    output reg btnTest,
    output reg [3:0] contBtnPress
);

localparam PRESSING = 3'd0; // 0
localparam WAITING = 3'd1;   // 1
localparam COUNTING = 3'd2;   // 2

reg [3:0] state;
reg [3:0] next;

reg [$clog2(COUNT_MAX)-1:0] counter;
reg [3:0] contmsegs;
reg clkmseg;

reg prevBotonTest;

initial begin
    state <= PRESSING;
    next <= PRESSING;
end

//Reset de la máquina de estados
always @(posedge clk or posedge rst) begin
    if (rst) begin
        state <= PRESSING;
    end else begin
        state <= next;
    end
end

// Máquina de Estados , general: Cambio entre estados
always @(posedge clk or posedge rst) begin
    case(state)
        PRESSING: begin
            btnTest <= 0;
            contBtnPress <= 0;
            if (botonTest) begin
                next <= WAITING;
                counter <= 0;
                contmsegs <= 0;
            end else begin
                next <= PRESSING;
            end
        end
        WAITING: begin
            if (!botonTest) begin
                next <= PRESSING;
            end else begin
                if (contmsegs < FiveSegs) begin
                    next <= WAITING;
                end else begin
                    btnTest <= 1;
                    contmsegs <= 0;
                    prevBotonTest <= botonTest;
                    next <= COUNTING;
                end
            end
        end
        COUNTING: begin
            btnTest <= 0;
            if (contmsegs < FiveSegs) begin
                next = COUNTING;
            end else begin
                next <= PRESSING;
            end

            prevBotonTest <= botonTest;
            if (botonTest && !prevBotonTest) begin
                contBtnPress <= contBtnPress + 1;
            end
        end
    endcase
end


// Divisor de frecuencia , a reloj en s
always @(posedge clk or posedge rst) begin
if(rst)begin
    clkmseg <=0;
    counter <=0;
end else begin
if (counter == COUNT_MAX-1) begin
    clkmseg <= ~clkmseg;
    counter <= 0;
    end else begin
        counter = counter +1;
    end
end
end

// Contador de tiempo en general 
always @(posedge clkmseg or posedge rst) begin
if(rst)begin
    contmsegs <= 0;
end else begin
    contmsegs <= contmsegs+1;
end
end



endmodule

ProyectoQuartus/src/Botones/bttnTestTB.v
`timescale 1ns / 1ps
`include "/home/samarinbe/Desktop/LabsDig1/entrega-1-proyecto-grupo01-2024-1/ProyectoQuartus/src/UnidadDeControl/bttnTest.v"

module bttnTestTB;

    // Inputs
    reg clk;
    reg rst;
    reg botonTest;
    wire btnTest;
    wire contBtnPress;

    // Instantiate the module under test
    bttnTest #(1, 5) uut(
        .clk(clk),
        .rst(rst),
        .botonTest(botonTest),
        .btnTest(btnTest)
    );

    // Clock generation
	always #5 clk = ~clk;

    initial begin
        clk = 0;
        botonTest = 0;
        #5
        rst = 1;
        #10 rst = 0;

        #10 botonTest = 1;
        #10 botonTest = 0;

        #10 botonTest = 1;
        #10 botonTest = 0;

        #10 botonTest = 1;
        #10 botonTest = 0;

        #20 botonTest = 1;
        #100 botonTest = 0;

        #30 botonTest = 1;
        #10 botonTest = 0;

        #10 botonTest = 1;
        #10 botonTest = 0;

        #10 botonTest = 1;
        #10 botonTest = 0;

        #50 botonTest = 1;
        #110 botonTest = 0;

        #30 botonTest = 1;
        #10 botonTest = 0;

        #10 botonTest = 1;
        #10 botonTest = 0;

        #10 botonTest = 1;
        #10 botonTest = 0;

        #10 botonTest = 1;
        #10 botonTest = 0;

    end

    initial begin:TEST_CASE
    $dumpfile("bttnTestTB.vcd");
	$dumpvars(-1, uut);
	#1000 $finish; 
end


endmodule

src/UnidadDeControl/bttnTestTB.vcd
$date
	Sat Aug 17 17:43:19 2024
$end
$version
	Icarus Verilog
$end
$timescale
	1ps
$end
$scope module bttnTestTB $end
$scope module uut $end
$var wire 1 ! botonTest $end
$var wire 1 " clk $end
$var wire 1 # rst $end
$var parameter 3 $ COUNTING $end
$var parameter 32 % COUNT_MAX $end
$var parameter 32 & FiveSegs $end
$var parameter 3 ' PRESSING $end
$var parameter 3 ( WAITING $end
$var reg 1 ) btnTest $end
$var reg 1 * clkmseg $end
$var reg 4 + contBtnPress [3:0] $end
$var reg 4 , contmsegs [3:0] $end
$var reg 2 - counter [-1:0] $end
$var reg 4 . next [3:0] $end
$var reg 1 / prevBotonTest $end
$var reg 4 0 state [3:0] $end
$upscope $end
$upscope $end
$enddefinitions $end
$comment Show the parameter values. $end
$dumpall
b1 (
b0 '
b101 &
b1 %
b10 $
$end
#0
$dumpvars
b0 0
x/
b0 .
bx -
bx ,
bx +
x*
x)
x#
0"
0!
$end
#5000
b0 ,
b0 +
0)
b0 -
0*
1#
1"
#10000
0"
#15000
b1 ,
1*
1"
0#
#20000
0"
#25000
b0 ,
b1 .
0*
1"
1!
#30000
0"
#35000
b1 ,
1*
b0 .
b1 0
1"
0!
#40000
0"
#45000
b0 0
b1 .
0*
1"
1!
#50000
0"
#55000
b10 ,
1*
b0 .
b1 0
1"
0!
#60000
0"
#65000
b0 0
b1 .
0*
1"
1!
#70000
0"
#75000
b11 ,
1*
b0 .
b1 0
1"
0!
#80000
0"
#85000
b0 0
b1 .
0*
1"
1!
#90000
0"
#95000
1*
b1 ,
b1 0
1"
#100000
0"
#105000
0*
1"
#110000
0"
#115000
b10 ,
1*
1"
#120000
0"
#125000
0*
1"
#130000
0"
#135000
b11 ,
1*
1"
#140000
0"
#145000
0*
1"
#150000
0"
#155000
b100 ,
1*
1"
#160000
0"
#165000
0*
1"
#170000
0"
#175000
b101 ,
1*
1"
#180000
0"
#185000
b10 .
1/
b0 ,
1)
0*
1"
#190000
0"
#195000
b1 ,
1*
b0 .
b10 0
1"
0!
#200000
0"
#205000
0/
0)
0*
b10 .
1"
#210000
0"
#215000
b10 ,
1*
1"
#220000
0"
#225000
b1 +
1/
0*
1"
1!
#230000
0"
#235000
b11 ,
1*
0/
1"
0!
#240000
0"
#245000
b10 +
1/
0*
1"
1!
#250000
0"
#255000
b100 ,
1*
0/
1"
0!
#260000
0"
#265000
b11 +
1/
0*
1"
1!
#270000
0"
#275000
b101 ,
1*
0/
1"
0!
#280000
0"
#285000
b0 .
0*
1"
#290000
0"
#295000
b110 ,
1*
b0 0
1"
#300000
0"
#305000
b0 +
0*
1"
#310000
0"
#315000
b111 ,
1*
1"
#320000
0"
#325000
b0 ,
b1 .
0*
1"
1!
#330000
0"
#335000
b1 ,
1*
b1 0
1"
#340000
0"
#345000
0*
1"
#350000
0"
#355000
b10 ,
1*
1"
#360000
0"
#365000
0*
1"
#370000
0"
#375000
b11 ,
1*
1"
#380000
0"
#385000
0*
1"
#390000
0"
#395000
b100 ,
1*
1"
#400000
0"
#405000
0*
1"
#410000
0"
#415000
b101 ,
1*
1"
#420000
0"
#425000
b10 .
1/
b0 ,
1)
0*
1"
#430000
0"
#435000
b1 ,
1*
b0 .
b10 0
1"
0!
#440000
0"
#445000
0/
0)
0*
b10 .
1"
#450000
0"
#455000
b10 ,
1*
1"
#460000
0"
#465000
b1 +
1/
0*
1"
1!
#470000
0"
#475000
b11 ,
1*
0/
1"
0!
#480000
0"
#485000
b10 +
1/
0*
1"
1!
#490000
0"
#495000
b100 ,
1*
0/
1"
0!
#500000
0"
#505000
b11 +
1/
0*
1"
1!
#510000
0"
#515000
b101 ,
1*
0/
1"
0!
#520000
0"
#525000
b100 +
1/
b0 .
0*
1"
1!
#530000
0"
#535000
b110 ,
1*
0/
b0 0
1"
0!
#540000
0"
#545000
b0 +
0*
1"
#550000
0"
#555000
b111 ,
1*
1"
#560000
0"
#565000
0*
1"
#570000
0"
#575000
b1000 ,
1*
1"
#580000
0"
#585000
0*
1"
#590000
0"
#595000
b1001 ,
1*
1"
#600000
0"
#605000
0*
1"
#610000
0"
#615000
b1010 ,
1*
1"
#620000
0"
#625000
0*
1"
#630000
0"
#635000
b1011 ,
1*
1"
#640000
0"
#645000
0*
1"
#650000
0"
#655000
b1100 ,
1*
1"
#660000
0"
#665000
0*
1"
#670000
0"
#675000
b1101 ,
1*
1"
#680000
0"
#685000
0*
1"
#690000
0"
#695000
b1110 ,
1*
1"
#700000
0"
#705000
0*
1"
#710000
0"
#715000
b1111 ,
1*
1"
#720000
0"
#725000
0*
1"
#730000
0"
#735000
b0 ,
1*
1"
#740000
0"
#745000
0*
1"
#750000
0"
#755000
b1 ,
1*
1"
#760000
0"
#765000
0*
1"
#770000
0"
#775000
b10 ,
1*
1"
#780000
0"
#785000
0*
1"
#790000
0"
#795000
b11 ,
1*
1"
#800000
0"
#805000
0*
1"
#810000
0"
#815000
b100 ,
1*
1"
#820000
0"
#825000
0*
1"
#830000
0"
#835000
b101 ,
1*
1"
#840000
0"
#845000
0*
1"
#850000
0"
#855000
b110 ,
1*
1"
#860000
0"
#865000
0*
1"
#870000
0"
#875000
b111 ,
1*
1"
#880000
0"
#885000
0*
1"
#890000
0"
#895000
b1000 ,
1*
1"
#900000
0"
#905000
0*
1"
#910000
0"
#915000
b1001 ,
1*
1"
#920000
0"
#925000
0*
1"
#930000
0"
#935000
b1010 ,
1*
1"
#940000
0"
#945000
0*
1"
#950000
0"
#955000
b1011 ,
1*
1"
#960000
0"
#965000
0*
1"
#970000
0"
#975000
b1100 ,
1*
1"
#980000
0"
#985000
0*
1"
#990000
0"
#995000
b1101 ,
1*
1"
